scratch_text_to_nums/__init__.py
scratch_text_to_nums-0.1.8.dist-info/WHEEL
scratch_text_to_nums-0.1.8.dist-info/METADATA
scratch_text_to_nums-0.1.8.dist-info/RECORD
