Metadata-Version: 2.1
Name: scratch-text-to-nums
Version: 0.1.8
Summary: Encodes strings to send to the Scratch cloud
Author: joecooldoo
Requires-Python: >=3.8,<4.0
Classifier: Programming Language :: Python :: 3
Classifier: Programming Language :: Python :: 3.8
Classifier: Programming Language :: Python :: 3.9
